{"is_source_file": false, "format": "", "description": "", "external_files": [], "external_methods": [], "published": [], "classes": [], "methods": [], "calls": [], "search-terms": [], "state": 2, "file_id": 10, "knowledge_revision": 17, "git_revision": "b81d7595244d72d201069b5f11e9cef45d39338b", "hash": "db949b4e7ac4655fb197fff26164fcbe", "format-version": 4, "code-base-name": "tic_tac_toe_frontend", "filename": "README.md", "revision_history": [{"17": "b81d7595244d72d201069b5f11e9cef45d39338b"}]}